qafs/__init__.py
qafs/base.py
qafs/connection.py
qafs/core.py
qafs/exceptions.py
qafs/model.py
qafs/timeseries.py
qafs/upgrade.py
qafs/utils.py
qafs/version.py
qafs/storage/__init__.py
qafs/storage/_base.py
qafs/storage/dask.py
qafs/storage/pandas.py
qafs-0.1.1.data/data/LICENSE
qafs-0.1.1.data/data/README.md
qafs-0.1.1.data/data/VERSION
qafs-0.1.1.dist-info/LICENSE
qafs-0.1.1.dist-info/METADATA
qafs-0.1.1.dist-info/WHEEL
qafs-0.1.1.dist-info/top_level.txt
qafs-0.1.1.dist-info/RECORD
