Metadata-Version: 2.1
Name: qafs
Version: 0.1.1
Summary: Quality Aware Feature Store.
Home-page: https://github.com/rodrigobaron/qafs
Author: Rodrigo Baron
Author-email: baron.rodrigo0@gmail.com
License: GPL-3.0
Platform: UNKNOWN
Classifier: Development Status :: 4 - Beta
Classifier: Intended Audience :: Developers
Classifier: Intended Audience :: Science/Research
Classifier: License :: OSI Approved :: Apache Software License
Classifier: Operating System :: OS Independent
Classifier: Programming Language :: Python :: 3
Classifier: Programming Language :: Python :: 3.7
Classifier: Programming Language :: Python :: 3.8
Classifier: Programming Language :: Python :: 3.9
Classifier: Topic :: Scientific/Engineering :: Artificial Intelligence
Requires-Python: >=3.7
License-File: LICENSE
Requires-Dist: pandas (>=1.1)
Requires-Dist: pyarrow (>=3.0)
Requires-Dist: dask[dataframe,delayed] (>=2021)
Requires-Dist: SQLAlchemy (>=1.3)
Requires-Dist: alembic (>=1.5)
Requires-Dist: requests (>=2)
Requires-Dist: requests-oauthlib (>=1.1)
Requires-Dist: cloudpickle
Requires-Dist: pandera[io] (>=0.8.1)
Provides-Extra: dev
Requires-Dist: pytest (==6.2.5) ; extra == 'dev'
Requires-Dist: pytest-cov (==3.0.0) ; extra == 'dev'
Requires-Dist: mock (==4.0.3) ; extra == 'dev'
Requires-Dist: black (==21.12b0) ; extra == 'dev'
Requires-Dist: flake8 (==4.0.1) ; extra == 'dev'
Requires-Dist: mypy (==0.930) ; extra == 'dev'
Requires-Dist: isort (==5.10.1) ; extra == 'dev'
